news_inspector/__init__.py
news_inspector/classifiers.py
news_inspector/core.py
news_inspector/knowledge_base.py
news_inspector/nlp.py
news_inspector/retrieval.py
news_inspector-0.1.1.dist-info/LICENSE
news_inspector-0.1.1.dist-info/METADATA
news_inspector-0.1.1.dist-info/WHEEL
news_inspector-0.1.1.dist-info/top_level.txt
news_inspector-0.1.1.dist-info/RECORD
