Metadata-Version: 2.1
Name: news-inspector
Version: 0.1.1
Summary: News-inspector is a library for analyzing and extracting information from news articles
Home-page: https://github.com/rdorado/news-inspector
Author: Ruben Dorado
Author-email: ruben.dorados@gmail.com
License: UNKNOWN
Platform: UNKNOWN
Classifier: Programming Language :: Python :: 3
Classifier: License :: OSI Approved :: BSD License
Classifier: Operating System :: OS Independent
Requires-Dist: scikit-learn (>=0.17.1)
Requires-Dist: sklearn-crfsuite (>=0.3)
Requires-Dist: nltk (>=3.2)
